{"v":"5.7.1","fr":29.9700012207031,"ip":0,"op":135.000005498663,"w":434,"h":194,"nm":"Композиция 1","ddd":0,"assets":[],"layers":[{"ddd":0,"ind":1,"ty":4,"nm":"Кривые 404","sr":1,"ks":{"o":{"a":0,"k":100,"ix":11},"r":{"a":0,"k":0,"ix":10},"p":{"a":0,"k":[217,97,0],"ix":2},"a":{"a":0,"k":[214,79,0],"ix":1},"s":{"a":0,"k":[100,100,100],"ix":6}},"ao":0,"shapes":[{"ty":"gr","it":[{"ind":0,"ty":"sh","ix":1,"ks":{"a":0,"k":{"i":[[0,0],[0,0],[0,0],[0,0],[0,0],[0,0],[0,0],[0,0],[0,0],[0,0],[0,0],[0,0],[0,0],[0,0],[0,0],[0,0],[0,0],[0,0],[0,0],[0,0],[0,0],[0,0],[0,0],[0,0],[0,0],[0,0],[0,0],[0,0],[0,0],[0,0],[0,0],[0,0],[0,0],[0,0],[0,0]],"o":[[0,0],[0,0],[0,0],[0,0],[0,0],[0,0],[0,0],[0,0],[0,0],[0,0],[0,0],[0,0],[0,0],[0,0],[0,0],[0,0],[0,0],[0,0],[0,0],[0,0],[0,0],[0,0],[0,0],[0,0],[0,0],[0,0],[0,0],[0,0],[0,0],[0,0],[0,0],[0,0],[0,0],[0,0],[0,0]],"v":[[69.751,15.098],[69.751,14.348],[69.001,14.348],[45.51,14.348],[45.51,-12.758],[45.51,-13.508],[44.76,-13.508],[12.226,-13.508],[11.476,-13.508],[11.476,-12.758],[11.476,14.348],[-26.278,14.348],[37.925,-73.984],[38.79,-75.174],[37.318,-75.174],[1.169,-75.174],[0.792,-75.174],[0.567,-74.872],[-69.603,19.54],[-69.752,19.741],[-69.752,19.989],[-69.752,43.165],[-69.752,43.915],[-69.002,43.915],[10.413,43.915],[10.413,74.424],[10.413,75.174],[11.163,75.174],[44.76,75.174],[45.51,75.174],[45.51,74.424],[45.51,43.915],[69.001,43.915],[69.751,43.915],[69.751,43.165]],"c":true},"ix":2},"nm":"Контур 1","mn":"ADBE Vector Shape - Group","hd":false},{"ty":"st","c":{"a":0,"k":[0.128999986836,0.128999986836,0.128999986836,1],"ix":3},"o":{"a":0,"k":100,"ix":4},"w":{"a":0,"k":1.5,"ix":5},"lc":1,"lj":1,"ml":4,"bm":0,"nm":"Обводка 1","mn":"ADBE Vector Graphic - Stroke","hd":false},{"ty":"tr","p":{"a":0,"k":[357.001,76.424],"ix":2},"a":{"a":0,"k":[0,0],"ix":1},"s":{"a":0,"k":[100,100],"ix":3},"r":{"a":0,"k":0,"ix":6},"o":{"a":0,"k":100,"ix":7},"sk":{"a":0,"k":0,"ix":4},"sa":{"a":0,"k":0,"ix":5},"nm":"Преобразовать"}],"nm":"Группа 1","np":2,"cix":2,"bm":0,"ix":1,"mn":"ADBE Vector Group","hd":false},{"ty":"gr","it":[{"ind":0,"ty":"sh","ix":1,"ks":{"a":0,"k":{"i":[[8.375,0],[4.959,7.514],[0,16.837],[-4.988,7.559],[-8.265,0],[-4.984,-7.513],[0,-16.837],[5.013,-7.56]],"o":[[-8.265,0],[-4.988,-7.561],[0,-16.836],[4.959,-7.515],[8.375,0],[5.013,7.559],[0,16.837],[-4.984,7.513]],"v":[[0,47.094],[-20.213,36.188],[-28.169,-0.001],[-20.213,-36.188],[0,-47.094],[20.4,-36.186],[28.382,-0.001],[20.4,36.187]],"c":true},"ix":2},"nm":"Контур 1","mn":"ADBE Vector Shape - Group","hd":false},{"ind":1,"ty":"sh","ix":2,"ks":{"a":0,"k":{"i":[[-18.489,0],[-11.503,13.281],[0,24.694],[11.495,13.272],[18.594,0],[11.529,-13.28],[0,-24.695],[-11.521,-13.272]],"o":[[18.594,0],[11.495,-13.272],[0,-24.693],[-11.503,-13.28],[-18.489,0],[-11.521,13.271],[0,24.696],[11.529,13.28]],"v":[[0,77.725],[46.258,57.398],[64.542,-0.001],[46.258,-57.399],[0,-77.725],[-46.178,-57.399],[-64.542,-0.001],[-46.178,57.4]],"c":true},"ix":2},"nm":"Контур 2","mn":"ADBE Vector Shape - Group","hd":false},{"ty":"mm","mm":1,"nm":"Объединить контуры 1","mn":"ADBE Vector Filter - Merge","hd":false},{"ty":"st","c":{"a":0,"k":[0.128999986836,0.128999986836,0.128999986836,1],"ix":3},"o":{"a":0,"k":100,"ix":4},"w":{"a":0,"k":1.5,"ix":5},"lc":1,"lj":1,"ml":4,"bm":0,"nm":"Обводка 1","mn":"ADBE Vector Graphic - Stroke","hd":false},{"ty":"tr","p":{"a":1,"k":[{"i":{"x":0.667,"y":1},"o":{"x":0.333,"y":0},"t":0,"s":[213.792,78.976],"to":[-2.5,0],"ti":[2.5,2.5]},{"i":{"x":0.667,"y":1},"o":{"x":0.333,"y":0},"t":15,"s":[198.792,78.976],"to":[-2.5,-2.5],"ti":[-5,2.5]},{"i":{"x":0.667,"y":1},"o":{"x":0.333,"y":0},"t":30,"s":[198.792,63.976],"to":[5,-2.5],"ti":[-5,-5]},{"i":{"x":0.667,"y":1},"o":{"x":0.333,"y":0},"t":45,"s":[228.792,63.976],"to":[5,5],"ti":[2.5,-5]},{"i":{"x":0.667,"y":1},"o":{"x":0.333,"y":0},"t":60,"s":[228.792,93.976],"to":[-2.5,5],"ti":[5,0]},{"i":{"x":0.667,"y":1},"o":{"x":0.333,"y":0},"t":75,"s":[213.792,93.976],"to":[-5,0],"ti":[2.5,2.5]},{"i":{"x":0.667,"y":1},"o":{"x":0.333,"y":0},"t":90,"s":[198.792,93.976],"to":[-2.5,-2.5],"ti":[0,5]},{"i":{"x":0.667,"y":1},"o":{"x":0.333,"y":0},"t":105,"s":[198.792,78.976],"to":[0,-5],"ti":[-2.5,2.5]},{"i":{"x":0.667,"y":1},"o":{"x":0.333,"y":0},"t":120,"s":[198.792,63.976],"to":[2.5,-2.5],"ti":[-2.5,0]},{"t":135.000005498663,"s":[213.792,63.976]}],"ix":2},"a":{"a":0,"k":[0,0],"ix":1},"s":{"a":0,"k":[100,100],"ix":3},"r":{"a":0,"k":0,"ix":6},"o":{"a":0,"k":100,"ix":7},"sk":{"a":0,"k":0,"ix":4},"sa":{"a":0,"k":0,"ix":5},"nm":"Преобразовать"}],"nm":"Группа 2","np":4,"cix":2,"bm":0,"ix":2,"mn":"ADBE Vector Group","hd":false},{"ty":"gr","it":[{"ind":0,"ty":"sh","ix":1,"ks":{"a":0,"k":{"i":[[0,0],[0,0],[0,0],[0,0],[0,0],[0,0],[0,0],[0,0],[0,0],[0,0],[0,0],[0,0],[0,0],[0,0],[0,0],[0,0],[0,0],[0,0],[0,0],[0,0],[0,0],[0,0],[0,0],[0,0],[0,0],[0,0],[0,0],[0,0],[0,0],[0,0],[0,0],[0,0],[0,0],[0,0],[0,0]],"o":[[0,0],[0,0],[0,0],[0,0],[0,0],[0,0],[0,0],[0,0],[0,0],[0,0],[0,0],[0,0],[0,0],[0,0],[0,0],[0,0],[0,0],[0,0],[0,0],[0,0],[0,0],[0,0],[0,0],[0,0],[0,0],[0,0],[0,0],[0,0],[0,0],[0,0],[0,0],[0,0],[0,0],[0,0],[0,0]],"v":[[69.752,15.098],[69.752,14.348],[69.002,14.348],[45.51,14.348],[45.51,-12.758],[45.51,-13.508],[44.76,-13.508],[12.227,-13.508],[11.477,-13.508],[11.477,-12.758],[11.477,14.348],[-26.277,14.348],[37.924,-73.984],[38.79,-75.174],[37.319,-75.174],[1.17,-75.174],[0.793,-75.174],[0.568,-74.872],[-69.604,19.54],[-69.752,19.741],[-69.752,19.989],[-69.752,43.165],[-69.752,43.915],[-69.002,43.915],[10.413,43.915],[10.413,74.424],[10.413,75.174],[11.163,75.174],[44.76,75.174],[45.51,75.174],[45.51,74.424],[45.51,43.915],[69.002,43.915],[69.752,43.915],[69.752,43.165]],"c":true},"ix":2},"nm":"Контур 1","mn":"ADBE Vector Shape - Group","hd":false},{"ty":"st","c":{"a":0,"k":[0.128999986836,0.128999986836,0.128999986836,1],"ix":3},"o":{"a":0,"k":100,"ix":4},"w":{"a":0,"k":1.5,"ix":5},"lc":1,"lj":1,"ml":4,"bm":0,"nm":"Обводка 1","mn":"ADBE Vector Graphic - Stroke","hd":false},{"ty":"tr","p":{"a":0,"k":[70.594,76.424],"ix":2},"a":{"a":0,"k":[0,0],"ix":1},"s":{"a":0,"k":[100,100],"ix":3},"r":{"a":0,"k":0,"ix":6},"o":{"a":0,"k":100,"ix":7},"sk":{"a":0,"k":0,"ix":4},"sa":{"a":0,"k":0,"ix":5},"nm":"Преобразовать"}],"nm":"Группа 3","np":2,"cix":2,"bm":0,"ix":3,"mn":"ADBE Vector Group","hd":false}],"ip":0,"op":135.000005498663,"st":0,"bm":0}],"markers":[]}